python_simple_email_sender/__init__.py
python_simple_email_sender/gmail_sender.py
python_simple_email_sender-1.0.6.dist-info/licenses/LICENSE
python_simple_email_sender-1.0.6.dist-info/METADATA
python_simple_email_sender-1.0.6.dist-info/WHEEL
python_simple_email_sender-1.0.6.dist-info/top_level.txt
python_simple_email_sender-1.0.6.dist-info/RECORD
