Metadata-Version: 2.4
Name: python-simple-email-sender
Version: 1.0.6
Summary: Enhanced Gmail sender
Home-page: https://github.com/aviz92/python-simple-email-sender
Author: Avi Zaguri
Author-email: 
Project-URL: Repository, https://github.com/aviz92/python-simple-email-sender
Requires-Python: >=3.11
License-File: LICENSE
Requires-Dist: setuptools
Requires-Dist: wheel
Requires-Dist: python-dotenv
Requires-Dist: pre-commit
Requires-Dist: custom-python-logger
Dynamic: author
Dynamic: description
Dynamic: description-content-type
Dynamic: home-page
Dynamic: license-file
Dynamic: project-url
Dynamic: requires-dist
Dynamic: requires-python
Dynamic: summary
